hsdata
