Metadata-Version: 1.1
Name: hsdata
Version: 0.2.12
Summary: 用数据玩炉石！快速收集和分析炉石传说的卡牌及卡组数据。
Home-page: https://github.com/youfou/hsdata
Author: Youfou
Author-email: youfou@qq.com
License: Apache 2.0
Keywords: 炉石,Hearthstone,数据
Platform: UNKNOWN
Classifier: Development Status :: 4 - Beta
Classifier: License :: OSI Approved :: Apache Software License
Classifier: Programming Language :: Python :: 3
Classifier: Operating System :: OS Independent
Classifier: Natural Language :: Chinese (Simplified)
Classifier: Topic :: Games/Entertainment :: Simulation
Classifier: Topic :: Scientific/Engineering :: Information Analysis
